matter_tool/__init__.py
matter_tool/__main__.py
matter_tool/cli.py
matter_tool/error.py
matter_tool/api/ChipToolMgr.py
matter_tool/api/OTBRMgr.py
matter_tool/api/__init__.py
matter_tool/api/struct/ChipToolData.py
matter_tool/api/struct/OTBRData.py
matter_tool/api/struct/__init__.py
matter_tool/extlib/__init__.py
matter_tool/extlib/CMDAccess/CMDAccess.py
matter_tool/extlib/CMDAccess/__init__.py
matter_tool/extlib/CMDAccess/struct/CMD_data.py
matter_tool/extlib/CMDAccess/struct/ChipToolData.py
matter_tool/extlib/CMDAccess/struct/__init__.py
matter_tool/extlib/MgmtExt/__init__.py
matter_tool/extlib/MgmtExt/log.py
matter_tool/extlib/MgmtExt/time.py
matter_tool/extlib/TyperExt/TyperExt.py
matter_tool/extlib/TyperExt/__init__.py
matter_tool/module/__init__.py
matter_tool/module/data/Database.py
matter_tool/module/data/MatterDM.py
matter_tool/module/data/__init__.py
rafaelmicro_matter_tool-0.0.3.dist-info/METADATA
rafaelmicro_matter_tool-0.0.3.dist-info/WHEEL
rafaelmicro_matter_tool-0.0.3.dist-info/entry_points.txt
rafaelmicro_matter_tool-0.0.3.dist-info/top_level.txt
rafaelmicro_matter_tool-0.0.3.dist-info/RECORD
